README
setup.py
notmuch_abook.egg-info/PKG-INFO
notmuch_abook.egg-info/SOURCES.txt
notmuch_abook.egg-info/dependency_links.txt
notmuch_abook.egg-info/entry_points.txt
notmuch_abook.egg-info/namespace_packages.txt
notmuch_abook.egg-info/not-zip-safe
notmuch_abook.egg-info/pbr.json
notmuch_abook.egg-info/requires.txt
notmuch_abook.egg-info/top_level.txt
pythonx/notmuch_abook.py