Metadata-Version: 1.1
Name: notmuch_abook
Version: 1.7
Summary: Notmuch addressbook
Home-page: https://github.com/guyzmo/notmuch-abook/
Author: Bernard `Guyzmo` Pratz
Author-email: guyzmo+notmuch@m0g.net
License: WTFPL
Keywords: notmuch addressbook vim
Platform: UNKNOWN
Classifier: Development Status :: 4 - Beta
Classifier: Environment :: Console
Classifier: License :: Freely Distributable
Classifier: Topic :: Communications :: Email :: Address Book
